{
  "head" : {
    "vars" : [ "position", "position_name_en", "position_name_hi", "positionType", "adminAreaTypes", "adminArea", "admin_area_en", "admin_area_hi", "positionSuperclass", "position_superclass_en", "position_superclass_hi", "body", "body_en", "body_hi" ]
  },
  "results" : {
    "bindings" : [ {
      "position" : {
        "type" : "uri",
        "value" : "http://www.wikidata.org/entity/Q16556694"
      },
      "position_name_en" : {
        "xml:lang" : "en",
        "type" : "literal",
        "value" : "member of the Lok Sabha"
      },
      "position_name_hi" : {
        "xml:lang" : "hi",
        "type" : "literal",
        "value" : "लोकसभा सदस्य"
      },
      "positionType" : {
        "type" : "uri",
        "value" : "http://www.wikidata.org/entity/Q4175034"
      },
      "adminAreaTypes" : {
        "type" : "literal",
        "value" : "Q6256"
      },
      "adminArea" : {
        "type" : "uri",
        "value" : "http://www.wikidata.org/entity/Q668"
      },
      "admin_area_en" : {
        "xml:lang" : "en",
        "type" : "literal",
        "value" : "India"
      },
      "admin_area_hi" : {
        "xml:lang" : "hi",
        "type" : "literal",
        "value" : "भारत"
      },
      "positionSuperclass" : {
        "type" : "uri",
        "value" : "http://www.wikidata.org/entity/Q486839"
      },
      "position_superclass_en" : {
        "xml:lang" : "en",
        "type" : "literal",
        "value" : "member of parliament"
      },
      "position_superclass_hi" : {
        "xml:lang" : "hi",
        "type" : "literal",
        "value" : "सांसद"
      },
      "body" : {
        "type" : "uri",
        "value" : "http://www.wikidata.org/entity/Q230003"
      },
      "body_en" : {
        "xml:lang" : "en",
        "type" : "literal",
        "value" : "Lok Sabha"
      },
      "body_hi" : {
        "xml:lang" : "hi",
        "type" : "literal",
        "value" : "लोक सभा"
      }
    }, {
      "position" : {
        "type" : "uri",
        "value" : "http://www.wikidata.org/entity/Q17324844"
      },
      "position_name_en" : {
        "xml:lang" : "en",
        "type" : "literal",
        "value" : "member of the Rajya Sabha"
      },
      "positionType" : {
        "type" : "uri",
        "value" : "http://www.wikidata.org/entity/Q4175034"
      },
      "adminAreaTypes" : {
        "type" : "literal",
        "value" : "Q6256"
      },
      "adminArea" : {
        "type" : "uri",
        "value" : "http://www.wikidata.org/entity/Q668"
      },
      "admin_area_en" : {
        "xml:lang" : "en",
        "type" : "literal",
        "value" : "India"
      },
      "admin_area_hi" : {
        "xml:lang" : "hi",
        "type" : "literal",
        "value" : "भारत"
      },
      "positionSuperclass" : {
        "type" : "uri",
        "value" : "http://www.wikidata.org/entity/Q486839"
      },
      "position_superclass_en" : {
        "xml:lang" : "en",
        "type" : "literal",
        "value" : "member of parliament"
      },
      "position_superclass_hi" : {
        "xml:lang" : "hi",
        "type" : "literal",
        "value" : "सांसद"
      },
      "body" : {
        "type" : "uri",
        "value" : "http://www.wikidata.org/entity/Q244730"
      },
      "body_en" : {
        "xml:lang" : "en",
        "type" : "literal",
        "value" : "Rajya Sabha"
      },
      "body_hi" : {
        "xml:lang" : "hi",
        "type" : "literal",
        "value" : "राज्यसभा"
      }
    }, {
      "position" : {
        "type" : "uri",
        "value" : "http://www.wikidata.org/entity/Q192711"
      },
      "position_name_en" : {
        "xml:lang" : "en",
        "type" : "literal",
        "value" : "Prime Minister of India"
      },
      "position_name_hi" : {
        "xml:lang" : "hi",
        "type" : "literal",
        "value" : "भारत के प्रधानमंत्री"
      },
      "adminAreaTypes" : {
        "type" : "literal",
        "value" : "Q6256"
      },
      "adminArea" : {
        "type" : "uri",
        "value" : "http://www.wikidata.org/entity/Q668"
      },
      "admin_area_en" : {
        "xml:lang" : "en",
        "type" : "literal",
        "value" : "India"
      },
      "admin_area_hi" : {
        "xml:lang" : "hi",
        "type" : "literal",
        "value" : "भारत"
      },
      "positionSuperclass" : {
        "type" : "uri",
        "value" : "http://www.wikidata.org/entity/Q14212"
      },
      "position_superclass_en" : {
        "xml:lang" : "en",
        "type" : "literal",
        "value" : "prime minister"
      },
      "position_superclass_hi" : {
        "xml:lang" : "hi",
        "type" : "literal",
        "value" : "प्रधानमन्त्री"
      },
      "body" : {
        "type" : "uri",
        "value" : "http://www.wikidata.org/entity/Q960484"
      },
      "body_en" : {
        "xml:lang" : "en",
        "type" : "literal",
        "value" : "Union Council of Ministers of India"
      },
      "body_hi" : {
        "xml:lang" : "hi",
        "type" : "literal",
        "value" : "भारत का मंत्रिमंडल"
      }
    }, {
      "position" : {
        "type" : "uri",
        "value" : "http://www.wikidata.org/entity/Q24461612"
      },
      "position_name_en" : {
        "xml:lang" : "en",
        "type" : "literal",
        "value" : "Member of the Delhi Legislative Assembly"
      },
      "position_name_hi" : {
        "xml:lang" : "hi",
        "type" : "literal",
        "value" : "दिल्ली विधान सभा के सदस्य"
      },
      "positionType" : {
        "type" : "uri",
        "value" : "http://www.wikidata.org/entity/Q4175034"
      },
      "adminAreaTypes" : {
        "type" : "literal",
        "value" : "Q6256"
      },
      "adminArea" : {
        "type" : "uri",
        "value" : "http://www.wikidata.org/entity/Q668"
      },
      "admin_area_en" : {
        "xml:lang" : "en",
        "type" : "literal",
        "value" : "India"
      },
      "admin_area_hi" : {
        "xml:lang" : "hi",
        "type" : "literal",
        "value" : "भारत"
      },
      "positionSuperclass" : {
        "type" : "uri",
        "value" : "http://www.wikidata.org/entity/Q3526627"
      },
      "position_superclass_en" : {
        "xml:lang" : "en",
        "type" : "literal",
        "value" : "Member of a Legislative Assembly of India"
      },
      "body" : {
        "type" : "uri",
        "value" : "http://www.wikidata.org/entity/Q3526627"
      },
      "body_en" : {
        "xml:lang" : "en",
        "type" : "literal",
        "value" : "Member of a Legislative Assembly of India"
      }
    }, {
      "position" : {
        "type" : "uri",
        "value" : "http://www.wikidata.org/entity/Q24546266"
      },
      "position_name_en" : {
        "xml:lang" : "en",
        "type" : "literal",
        "value" : "Member of the Odisha Legislative Assembly"
      },
      "position_name_hi" : {
        "xml:lang" : "hi",
        "type" : "literal",
        "value" : "ओडिशा विधान सभा के सदस्य"
      },
      "positionType" : {
        "type" : "uri",
        "value" : "http://www.wikidata.org/entity/Q4175034"
      },
      "adminAreaTypes" : {
        "type" : "literal",
        "value" : "Q6256"
      },
      "adminArea" : {
        "type" : "uri",
        "value" : "http://www.wikidata.org/entity/Q668"
      },
      "admin_area_en" : {
        "xml:lang" : "en",
        "type" : "literal",
        "value" : "India"
      },
      "admin_area_hi" : {
        "xml:lang" : "hi",
        "type" : "literal",
        "value" : "भारत"
      },
      "positionSuperclass" : {
        "type" : "uri",
        "value" : "http://www.wikidata.org/entity/Q3526627"
      },
      "position_superclass_en" : {
        "xml:lang" : "en",
        "type" : "literal",
        "value" : "Member of a Legislative Assembly of India"
      },
      "body" : {
        "type" : "uri",
        "value" : "http://www.wikidata.org/entity/Q3526627"
      },
      "body_en" : {
        "xml:lang" : "en",
        "type" : "literal",
        "value" : "Member of a Legislative Assembly of India"
      }
    }, {
      "position" : {
        "type" : "uri",
        "value" : "http://www.wikidata.org/entity/Q24547509"
      },
      "position_name_en" : {
        "xml:lang" : "en",
        "type" : "literal",
        "value" : "Member of the Sikkim Legislative Assembly"
      },
      "position_name_hi" : {
        "xml:lang" : "hi",
        "type" : "literal",
        "value" : "सिक्किम विधान सभा के सदस्य"
      },
      "positionType" : {
        "type" : "uri",
        "value" : "http://www.wikidata.org/entity/Q4175034"
      },
      "adminAreaTypes" : {
        "type" : "literal",
        "value" : "Q10864048"
      },
      "adminArea" : {
        "type" : "uri",
        "value" : "http://www.wikidata.org/entity/Q1505"
      },
      "admin_area_en" : {
        "xml:lang" : "en",
        "type" : "literal",
        "value" : "Sikkim"
      },
      "admin_area_hi" : {
        "xml:lang" : "hi",
        "type" : "literal",
        "value" : "सिक्किम"
      },
      "positionSuperclass" : {
        "type" : "uri",
        "value" : "http://www.wikidata.org/entity/Q486839"
      },
      "position_superclass_en" : {
        "xml:lang" : "en",
        "type" : "literal",
        "value" : "member of parliament"
      },
      "position_superclass_hi" : {
        "xml:lang" : "hi",
        "type" : "literal",
        "value" : "सांसद"
      },
      "body" : {
        "type" : "uri",
        "value" : "http://www.wikidata.org/entity/Q7513808"
      },
      "body_en" : {
        "xml:lang" : "en",
        "type" : "literal",
        "value" : "Sikkim Legislative Assembly"
      },
      "body_hi" : {
        "xml:lang" : "hi",
        "type" : "literal",
        "value" : "सिक्किम विधान सभा"
      }
    }, {
      "position" : {
        "type" : "uri",
        "value" : "http://www.wikidata.org/entity/Q24547509"
      },
      "position_name_en" : {
        "xml:lang" : "en",
        "type" : "literal",
        "value" : "Member of the Sikkim Legislative Assembly"
      },
      "position_name_hi" : {
        "xml:lang" : "hi",
        "type" : "literal",
        "value" : "सिक्किम विधान सभा के सदस्य"
      },
      "positionType" : {
        "type" : "uri",
        "value" : "http://www.wikidata.org/entity/Q4175034"
      },
      "adminAreaTypes" : {
        "type" : "literal",
        "value" : "Q10864048"
      },
      "adminArea" : {
        "type" : "uri",
        "value" : "http://www.wikidata.org/entity/Q1505"
      },
      "admin_area_en" : {
        "xml:lang" : "en",
        "type" : "literal",
        "value" : "Sikkim"
      },
      "admin_area_hi" : {
        "xml:lang" : "hi",
        "type" : "literal",
        "value" : "सिक्किम"
      },
      "positionSuperclass" : {
        "type" : "uri",
        "value" : "http://www.wikidata.org/entity/Q3526627"
      },
      "position_superclass_en" : {
        "xml:lang" : "en",
        "type" : "literal",
        "value" : "Member of a Legislative Assembly of India"
      },
      "body" : {
        "type" : "uri",
        "value" : "http://www.wikidata.org/entity/Q7513808"
      },
      "body_en" : {
        "xml:lang" : "en",
        "type" : "literal",
        "value" : "Sikkim Legislative Assembly"
      },
      "body_hi" : {
        "xml:lang" : "hi",
        "type" : "literal",
        "value" : "सिक्किम विधान सभा"
      }
    }, {
      "position" : {
        "type" : "uri",
        "value" : "http://www.wikidata.org/entity/Q55018650"
      },
      "position_name_en" : {
        "xml:lang" : "en",
        "type" : "literal",
        "value" : "Chief Minister of Sikkim"
      },
      "position_name_hi" : {
        "xml:lang" : "hi",
        "type" : "literal",
        "value" : "सिक्किम के मुख्यमंत्री"
      },
      "adminAreaTypes" : {
        "type" : "literal",
        "value" : "Q10864048"
      },
      "adminArea" : {
        "type" : "uri",
        "value" : "http://www.wikidata.org/entity/Q1505"
      },
      "admin_area_en" : {
        "xml:lang" : "en",
        "type" : "literal",
        "value" : "Sikkim"
      },
      "admin_area_hi" : {
        "xml:lang" : "hi",
        "type" : "literal",
        "value" : "सिक्किम"
      },
      "positionSuperclass" : {
        "type" : "uri",
        "value" : "http://www.wikidata.org/entity/Q5096847"
      },
      "position_superclass_en" : {
        "xml:lang" : "en",
        "type" : "literal",
        "value" : "Chief Minister"
      },
      "position_superclass_hi" : {
        "xml:lang" : "hi",
        "type" : "literal",
        "value" : "मुख्यमन्त्री"
      },
      "body" : {
        "type" : "uri",
        "value" : "http://www.wikidata.org/entity/Q55147396"
      },
      "body_en" : {
        "xml:lang" : "en",
        "type" : "literal",
        "value" : "Council of Ministers of Sikkim"
      },
      "body_hi" : {
        "xml:lang" : "hi",
        "type" : "literal",
        "value" : "सिक्किम विधान सभा"
      }
    } ]
  }
}