{
  "persons": [

  ],
  "organizations": [
    {
      "name": {
        "lang:en": "General Body of Kakinada Municipal Corporation"
      },
      "id": "Q58944964",
      "classification": "branch",
      "identifiers": [
        {
          "scheme": "wikidata",
          "identifier": "Q58944964"
        }
      ],
      "area_id": "Q58954675"
    }
  ],
  "areas": [
    {
      "id": "Q1159",
      "identifiers": [
        {
          "scheme": "MS_FB",
          "identifier": "country:in/state:ap"
        },
        {
          "scheme": "wikidata",
          "identifier": "Q1159"
        }
      ],
      "associated_wikidata_positions": [
        "Q1813083"
      ],
      "type": {
        "lang:en": "state of India",
        "lang:hi": "भारतीय राज्य"
      },
      "name": {
        "lang:en": "Andhra Pradesh",
        "lang:hi": "आन्ध्र प्रदेश"
      },
      "parent_id": "Q668"
    },
    {
      "id": "Q58954675",
      "identifiers": [
        {
          "scheme": "MS_FB",
          "identifier": "country:in/state:ap/municipality:kakinada"
        },
        {
          "scheme": "wikidata",
          "identifier": "Q58954675"
        }
      ],
      "associated_wikidata_positions": [
        "Q58944153"
      ],
      "type": {
        "lang:en": "municipal corporation area"
      },
      "name": {
        "lang:en": "Kakinada Municipal Corporation area"
      },
      "parent_id": "Q1159"
    },
    {
      "id": "Q668",
      "identifiers": [
        {
          "scheme": "MS_FB",
          "identifier": "country:in"
        },
        {
          "scheme": "wikidata",
          "identifier": "Q668"
        }
      ],
      "associated_wikidata_positions": [
        "Q192711"
      ],
      "type": {
        "lang:en": "country",
        "lang:hi": "देश"
      },
      "name": {
        "lang:hi": "भारत गणराज्य",
        "lang:en": "Republic of India"
      },
      "parent_id": null
    }
  ],
  "memberships": [

  ]
}
